mapp_tricks/__init__.py
mapp_tricks/cross_section_analysis/__init__.py
mapp_tricks/cross_section_analysis/data_models.py
mapp_tricks/cross_section_analysis/do_cs_ana.py
mapp_tricks/cross_section_analysis/equations.py
mapp_tricks/film_analyzer/__init__.py
mapp_tricks/film_analyzer/calibration_data.json
mapp_tricks/film_analyzer/film_analyzer.py
mapp_tricks/film_analyzer/old_film_reader.py
mapp_tricks/orbitos_utils/__init__.py
mapp_tricks/orbitos_utils/analyze_electrometer_data.py
mapp_tricks/peakfit/__init__.py
mapp_tricks/peakfit/core.py
mapp_tricks/peakfit/models.py
mapp_tricks/peakfit/parser.py
mapp_tricks/peakfit/plotting.py
mapp_tricks/spectrometer_calibrations/__init__.py
mapp_tricks/spectrometer_calibrations/HPGe/__init__.py
mapp_tricks/spectrometer_calibrations/HPGe/hpge_calib.py
mapp_tricks/spectrometer_calibrations/HPGe/hpge_calib_2025.py
mapp_tricks/spectrometer_calibrations/HPGe/calibration-data/HPGe_efficiency_data.csv
mapp_tricks/spectrometer_calibrations/HPGe/calibration-data/raw-data/calib-2026/calib_source_full_new.csv
mapp_tricks/spectrometer_calibrations/HPGe/create-calib/__init__.py
mapp_tricks/spectrometer_calibrations/x_ray/__init__.py
mapp_tricks/spectrometer_calibrations/x_ray/xray_calib.py
mapp_tricks/spectrometer_calibrations/x_ray/calibration-data/Source-data_Xray-spectrometer.csv
mapp_tricks/spectrometer_calibrations/x_ray/calibration-data/SDD Efficiency files/SDD_normalized-Efficiency_default.txt
mapp_tricks/spectrometer_calibrations/x_ray/calibration-data/SDD Efficiency files/SDD_normalized-Efficiency_point-source_all-levels.csv
mapp_tricks/spectrometer_calibrations/x_ray/calibration-data/SDD Efficiency files/SDD_normalized-Efficiency_point-source_with-air_all-levels.csv
mapp_tricks/spectrometer_calibrations/x_ray/calibration-data/attenuation/attenuation-coefficient-Be_NIST.txt
mapp_tricks/spectrometer_calibrations/x_ray/calibration-data/attenuation/attenuation-coefficient-Si_NIST.txt
mapp_tricks-0.1.13.dist-info/METADATA
mapp_tricks-0.1.13.dist-info/WHEEL
mapp_tricks-0.1.13.dist-info/top_level.txt
mapp_tricks-0.1.13.dist-info/RECORD
