Metadata-Version: 2.4
Name: mapp_tricks
Version: 0.1.13
Summary: Reusable code developed during my PhD in the Medical Applications of Particle Physics group at the University of Bern.
Author: Lars Eggimann
Author-email: Lars Eggimann <lars.eggimann@gmail.com>
Requires-Dist: pandas
Requires-Dist: numpy
Requires-Dist: scipy
Requires-Dist: scikit-image
Requires-Dist: uncertainties
Requires-Dist: matplotlib
Requires-Dist: plotly
Requires-Dist: tqdm
Dynamic: author
